<annotations><filename>192.png</filename><folder>images</folder><size><width>1200</width><height>800</height><depth>3</depth></size><object><name>plastic</name><pose>Unspecified</pose><truncated>0</truncated><difficult>0</difficult><bndbox><xmin>36.99999999999997</xmin><ymin>81.0</ymin><xmax>521.0</xmax><ymax>465.0</ymax></bndbox></object><object><name>paper</name><pose>Unspecified</pose><truncated>0</truncated><difficult>0</difficult><bndbox><xmin>627.0</xmin><ymin>57.00000000000003</ymin><xmax>1051.0</xmax><ymax>441.0</ymax></bndbox></object><object><name>metal</name><pose>Unspecified</pose><truncated>0</truncated><difficult>0</difficult><bndbox><xmin>30.99999999999997</xmin><ymin>400.0</ymin><xmax>515.0</xmax><ymax>784.0</ymax></bndbox></object><object><name>cardboard</name><pose>Unspecified</pose><truncated>0</truncated><difficult>0</difficult><bndbox><xmin>600.0000000000001</xmin><ymin>400.0</ymin><xmax>1012.0000000000001</xmax><ymax>784.0</ymax></bndbox></object></annotations>