<annotations><filename>700.png</filename><folder>images</folder><size><width>1200</width><height>800</height><depth>3</depth></size><object><name>cardboard</name><pose>Unspecified</pose><truncated>0</truncated><difficult>0</difficult><bndbox><xmin>143.00000000000006</xmin><ymin>110.00000000000001</ymin><xmax>483.00000000000006</xmax><ymax>355.00000000000006</ymax></bndbox></object><object><name>glass</name><pose>Unspecified</pose><truncated>0</truncated><difficult>0</difficult><bndbox><xmin>608.0</xmin><ymin>66.0</ymin><xmax>962.0</xmax><ymax>404.0</ymax></bndbox></object><object><name>trash</name><pose>Unspecified</pose><truncated>0</truncated><difficult>0</difficult><bndbox><xmin>93.0</xmin><ymin>432.0</ymin><xmax>605.0</xmax><ymax>816.0</ymax></bndbox></object><object><name>paper</name><pose>Unspecified</pose><truncated>0</truncated><difficult>0</difficult><bndbox><xmin>701.0000000000001</xmin><ymin>400.0</ymin><xmax>1124.0000000000002</xmax><ymax>784.0</ymax></bndbox></object></annotations>