<annotations><filename>702.png</filename><folder>images</folder><size><width>1200</width><height>800</height><depth>3</depth></size><object><name>cardboard</name><pose>Unspecified</pose><truncated>0</truncated><difficult>0</difficult><bndbox><xmin>143.00000000000006</xmin><ymin>110.00000000000001</ymin><xmax>483.00000000000006</xmax><ymax>355.00000000000006</ymax></bndbox></object><object><name>paper</name><pose>Unspecified</pose><truncated>0</truncated><difficult>0</difficult><bndbox><xmin>701.0000000000001</xmin><ymin>0.0</ymin><xmax>1124.0000000000002</xmax><ymax>384.0</ymax></bndbox></object><object><name>plastic</name><pose>Unspecified</pose><truncated>0</truncated><difficult>0</difficult><bndbox><xmin>0.0</xmin><ymin>447.0</ymin><xmax>512.0</xmax><ymax>796.0</ymax></bndbox></object><object><name>metal</name><pose>Unspecified</pose><truncated>0</truncated><difficult>0</difficult><bndbox><xmin>706.0</xmin><ymin>400.0</ymin><xmax>1193.0</xmax><ymax>770.0</ymax></bndbox></object></annotations>